ansibleconnect/__init__.py
ansibleconnect/ansible_config_adapter.py
ansibleconnect/ansiblehostadapter.py
ansibleconnect/connections.py
ansibleconnect/inventoryadapter.py
ansibleconnect/main.py
ansibleconnect/parser.py
ansibleconnect/tmuxpresenter.py
ansibleconnect-1.1.0.dist-info/LICENSE
ansibleconnect-1.1.0.dist-info/METADATA
ansibleconnect-1.1.0.dist-info/WHEEL
ansibleconnect-1.1.0.dist-info/entry_points.txt
ansibleconnect-1.1.0.dist-info/top_level.txt
ansibleconnect-1.1.0.dist-info/RECORD
