Metadata-Version: 2.1
Name: ansibleconnect
Version: 1.1.0
Summary: Connect to all hosts from the ansible inventory with one command
Home-page: https://github.com/psykulsk/ansibleconnect
Author: Piotr Sykulski
Author-email: pitersk@gmail.com
License: MIT
Classifier: License :: OSI Approved :: MIT License
Classifier: Programming Language :: Python :: 3
Classifier: Environment :: Console
Classifier: Intended Audience :: Developers
Classifier: Intended Audience :: Information Technology
Classifier: Intended Audience :: System Administrators
Classifier: Topic :: Utilities
Classifier: Topic :: System :: Systems Administration
License-File: LICENSE
Requires-Dist: PyYAML>=4.0
Requires-Dist: ansible
